nabo/__init__.py
nabo/_dataset.py
nabo/_graph.py
nabo/_graphplot.py
nabo/_io.py
nabo/_mapping.py
nabo/_marker.py
nabo/_plotting.py
nabo/_umap.py
nabo-0.4.1.data/scripts/nabo
nabo-0.4.1.dist-info/LICENSE
nabo-0.4.1.dist-info/METADATA
nabo-0.4.1.dist-info/WHEEL
nabo-0.4.1.dist-info/top_level.txt
nabo-0.4.1.dist-info/RECORD
