Metadata-Version: 2.1
Name: nabo
Version: 0.4.1
Summary: Python library to perform memory efficient cross-sample cell mapping using single cell transciptomics (scRNA-Seq) data
Home-page: https://github.com/parashardhapola/nabo
Author: Parashar Dhapola
Author-email: parashar.dhapola@gmail.com
Maintainer: Parashar Dhapola
Maintainer-email: parashar.dhapola@gmail.com
License: BSD 3-Clause
Keywords: scRNA-Seq,bioinformatics,single cell,analysis,graph,cell alignment,rna-seq,sequencing,shared nearest neighbors,knn,snn
Platform: UNKNOWN
Classifier: Development Status :: 4 - Beta
Classifier: License :: OSI Approved :: BSD License
Classifier: Natural Language :: English
Classifier: Operating System :: MacOS :: MacOS X
Classifier: Operating System :: Microsoft :: Windows
Classifier: Operating System :: POSIX :: Linux
Classifier: Programming Language :: Python :: 3
Classifier: Programming Language :: Python :: 3.6
Classifier: Programming Language :: Python :: 3.7
Classifier: Topic :: Scientific/Engineering :: Bio-Informatics
Classifier: Topic :: Scientific/Engineering :: Visualization
Requires-Dist: h5py
Requires-Dist: numpy
Requires-Dist: tqdm
Requires-Dist: pandas
Requires-Dist: statsmodels
Requires-Dist: sklearn
Requires-Dist: numba
Requires-Dist: networkx
Requires-Dist: fa2
Requires-Dist: AgglomCluster
Requires-Dist: matplotlib
Requires-Dist: seaborn
Requires-Dist: natsort
Requires-Dist: scipy
Requires-Dist: umap-learn
